README.rst
setup.py
bin/mdtree
mdtree/__init__.py
mdtree/main.py
mdtree/mdutils.py
mdtree/parser.py
mdtree.egg-info/PKG-INFO
mdtree.egg-info/SOURCES.txt
mdtree.egg-info/dependency_links.txt
mdtree.egg-info/requires.txt
mdtree.egg-info/top_level.txt
mdtree/static/css/base.css
mdtree/static/css/mdtree.min.css
mdtree/static/css/pygments.css
mdtree/static/html/template.html
mdtree/static/js/mdtree.min.js